gunicorn_prometheus_exporter/__init__.py
gunicorn_prometheus_exporter/hooks.py
gunicorn_prometheus_exporter/master.py
gunicorn_prometheus_exporter/metrics.py
gunicorn_prometheus_exporter/plugin.py
gunicorn_prometheus_exporter/utils.py
gunicorn_prometheus_exporter/backend/__init__.py
gunicorn_prometheus_exporter/backend/core/__init__.py
gunicorn_prometheus_exporter/backend/core/client.py
gunicorn_prometheus_exporter/backend/core/collector.py
gunicorn_prometheus_exporter/backend/core/dict.py
gunicorn_prometheus_exporter/backend/core/values.py
gunicorn_prometheus_exporter/backend/service/__init__.py
gunicorn_prometheus_exporter/backend/service/manager.py
gunicorn_prometheus_exporter/config/__init__.py
gunicorn_prometheus_exporter/config/loader.py
gunicorn_prometheus_exporter/config/manager.py
gunicorn_prometheus_exporter/config/settings.py
gunicorn_prometheus_exporter-0.2.4.dist-info/licenses/LICENSE
gunicorn_prometheus_exporter-0.2.4.dist-info/WHEEL
gunicorn_prometheus_exporter-0.2.4.dist-info/METADATA
gunicorn_prometheus_exporter-0.2.4.dist-info/RECORD
