Metadata-Version: 2.4
Name: gunicorn-prometheus-exporter
Version: 0.2.4
Summary: A comprehensive Prometheus metrics exporter for Gunicorn WSGI servers with innovative Redis-based storage, YAML configuration support, advanced signal handling, and support for all worker types (sync, thread, eventlet, gevent)
Author-email: Prince Roshan <princekrroshan01@gmail.com>
Requires-Python: >=3.9
License-Expression: MIT
Classifier: Development Status :: 4 - Beta
Classifier: Intended Audience :: Developers
Classifier: Programming Language :: Python :: 3
Classifier: Programming Language :: Python :: 3.9
Classifier: Programming Language :: Python :: 3.10
Classifier: Programming Language :: Python :: 3.11
Classifier: Programming Language :: Python :: 3.12
Classifier: Programming Language :: Python :: 3.13
License-File: LICENSE
Requires-Dist: prometheus-client>=0.20.0
Requires-Dist: psutil>=5.9.8
Requires-Dist: gunicorn>=21.2.0
Requires-Dist: PyYAML>=6.0.0
Requires-Dist: eventlet>=0.33.0 ; extra == "all"
Requires-Dist: gevent>=23.0.0 ; extra == "all"
Requires-Dist: redis>=4.0.0 ; extra == "all"
Requires-Dist: eventlet>=0.33.0 ; extra == "async"
Requires-Dist: gevent>=23.0.0 ; extra == "async"
Requires-Dist: pytest>=7.0.0 ; extra == "dev"
Requires-Dist: pytest-cov>=4.0.0 ; extra == "dev"
Requires-Dist: ruff>=0.1.0 ; extra == "dev"
Requires-Dist: xenon>=0.9.0 ; extra == "dev"
Requires-Dist: prospector>=1.10.0 ; extra == "dev"
Requires-Dist: radon>=6.0.0 ; extra == "dev"
Requires-Dist: bandit>=1.7.0 ; extra == "dev"
Requires-Dist: safety>=2.3.0 ; extra == "dev"
Requires-Dist: pre-commit>=3.5.0 ; extra == "dev"
Requires-Dist: isort>=5.13.0 ; extra == "dev"
Requires-Dist: redis>=4.0.0 ; extra == "dev"
Requires-Dist: PyYAML>=6.0.0 ; extra == "dev"
Requires-Dist: mkdocs>=1.5.0 ; extra == "docs"
Requires-Dist: mkdocs-material>=9.0.0 ; extra == "docs"
Requires-Dist: mkdocs-minify-plugin>=0.7.0 ; extra == "docs"
Requires-Dist: eventlet>=0.33.0 ; extra == "eventlet"
Requires-Dist: gevent>=23.0.0 ; extra == "gevent"
Requires-Dist: redis>=4.0.0 ; extra == "redis"
Project-URL: Documentation, https://github.com/Agent-Hellboy/gunicorn-prometheus-exporter#readme
Project-URL: Homepage, https://github.com/Agent-Hellboy/gunicorn-prometheus-exporter
Project-URL: Issues, https://github.com/Agent-Hellboy/gunicorn-prometheus-exporter/issues
Project-URL: Repository, https://github.com/Agent-Hellboy/gunicorn-prometheus-exporter.git
Provides-Extra: all
Provides-Extra: async
Provides-Extra: dev
Provides-Extra: docs
Provides-Extra: eventlet
Provides-Extra: gevent
Provides-Extra: redis
